setup.py
bibhupadpkgtest.egg-info/PKG-INFO
bibhupadpkgtest.egg-info/SOURCES.txt
bibhupadpkgtest.egg-info/dependency_links.txt
bibhupadpkgtest.egg-info/top_level.txt
myadipkg/__init__.py
myadipkg/calculator.py
myadipkg/setup.py