Metadata-Version: 2.1
Name: bibhupadpkgtest
Version: 0.0.1
Summary: ADI python package module
Home-page: https://github.com/bibhupadt/MyDemoPackage
Author: Bibhupad
Author-email: bibhupad@gmail.com
License: UNKNOWN
Platform: UNKNOWN
Classifier: Programming Language :: Python :: 3
Classifier: Operating System :: OS Independent
